clusttool/__init__.py
clusttool-0.1.2.dist-info/LICENSE
clusttool-0.1.2.dist-info/METADATA
clusttool-0.1.2.dist-info/WHEEL
clusttool-0.1.2.dist-info/top_level.txt
clusttool-0.1.2.dist-info/RECORD
