Metadata-Version: 2.1
Name: clusttool
Version: 0.1.2
Summary: A clustering toolbox package
Home-page: https://github.com/markoniem/clustering-toolbox
Author: Marko Niemela
Author-email: marko.nieme@gmail.com
License: UNKNOWN
Platform: UNKNOWN
Classifier: Programming Language :: Python :: 3
Classifier: License :: OSI Approved :: MIT License
Classifier: Operating System :: OS Independent
Requires-Python: >=3.5
